[
    {
        "end_device_ids": {
            "device_id": "em300-di",
            "application_ids": {
                "application_id": "daia-sensor-em300"
            },
            "dev_eui": "24E124136C482304",
            "join_eui": "24E124C0002A0001",
            "dev_addr": "260DA6E2"
        },
        "correlation_ids": [
            "gs:uplink:01JKPF92BJFWD2PQY2SMVBJPRG"
        ],
        "received_at": "2025-02-09T23:03:56.737496836Z",
        "uplink_message": {
            "session_key_id": "AZTN7na5Ikz11RtlE7G4bg==",
            "f_port": 85,
            "f_cnt": 1843,
            "frm_payload": "AXVjA2fvAARoTAXIBQsAAA==",
            "decoded_payload": {
                "battery": 99,
                "humidity": 38,
                "pulse": 2821,
                "temperature": 23.9
            },
            "rx_metadata": [
                {
                    "gateway_ids": {
                        "gateway_id": "daia-gateway",
                        "eui": "24E124FFFEFAF7FD"
                    },
                    "time": "2025-02-09T23:03:44.804Z",
                    "timestamp": 3243782681,
                    "rssi": -89,
                    "channel_rssi": -89,
                    "snr": 10.8,
                    "frequency_offset": "682",
                    "location": {
                        "latitude": -34.9861347413862,
                        "longitude": -71.238780895348,
                        "source": "SOURCE_REGISTRY"
                    },
                    "uplink_token": "ChoKGAoMZGFpYS1nYXRld2F5Eggk4ST//vr3/RCZ5OCKDBoMCNzopL0GEJa79vsBIKjjjoS083YqDAjQ6KS9BhCAorD/Ag==",
                    "channel_index": 2,
                    "gps_time": "2025-02-09T23:03:44.804Z",
                    "received_at": "2025-02-09T23:03:56.367611550Z"
                }
            ],
            "settings": {
                "data_rate": {
                    "lora": {
                        "bandwidth": 125000,
                        "spreading_factor": 7,
                        "coding_rate": "4/5"
                    }
                },
                "frequency": "917200000",
                "timestamp": 3243782681,
                "time": "2025-02-09T23:03:44.804Z"
            },
            "received_at": "2025-02-09T23:03:56.531705367Z",
            "consumed_airtime": "0.066816s",
            "network_ids": {
                "net_id": "000013",
                "ns_id": "EC656E0000000183",
                "tenant_id": "ttn",
                "cluster_id": "au1",
                "cluster_address": "au1.cloud.thethings.network"
            }
        }
    },
    {
        "end_device_ids": {
            "device_id": "em300-di",
            "application_ids": {
                "application_id": "daia-sensor-em300"
            },
            "dev_eui": "24E124136C482304",
            "join_eui": "24E124C0002A0001",
            "dev_addr": "260DA6E2"
        },
        "correlation_ids": [
            "gs:uplink:01JKPFJ7A1V464GMG610W7ADTQ"
        ],
        "received_at": "2025-02-09T23:08:56.720283557Z",
        "uplink_message": {
            "session_key_id": "AZTN7na5Ikz11RtlE7G4bg==",
            "f_port": 85,
            "f_cnt": 1844,
            "frm_payload": "AXVjA2fvAARoTAXIBQsAAA==",
            "decoded_payload": {
                "battery": 99,
                "humidity": 38,
                "pulse": 2821,
                "temperature": 23.9
            },
            "rx_metadata": [
                {
                    "gateway_ids": {
                        "gateway_id": "daia-gateway",
                        "eui": "24E124FFFEFAF7FD"
                    },
                    "time": "2025-02-09T23:08:44.785Z",
                    "timestamp": 3543766703,
                    "rssi": -88,
                    "channel_rssi": -88,
                    "snr": 7.8,
                    "frequency_offset": "694",
                    "location": {
                        "latitude": -34.9861347413862,
                        "longitude": -71.238780895348,
                        "source": "SOURCE_REGISTRY"
                    },
                    "uplink_token": "ChoKGAoMZGFpYS1nYXRld2F5Eggk4ST//vr3/RCvreaZDRoMCIjrpL0GEPDF6vMBIJi30seR/HYqDAj86qS9BhDAzKj2Ag==",
                    "channel_index": 1,
                    "gps_time": "2025-02-09T23:08:44.785Z",
                    "received_at": "2025-02-09T23:08:56.350639096Z"
                }
            ],
            "settings": {
                "data_rate": {
                    "lora": {
                        "bandwidth": 125000,
                        "spreading_factor": 7,
                        "coding_rate": "4/5"
                    }
                },
                "frequency": "917000000",
                "timestamp": 3543766703,
                "time": "2025-02-09T23:08:44.785Z"
            },
            "received_at": "2025-02-09T23:08:56.514646625Z",
            "consumed_airtime": "0.066816s",
            "network_ids": {
                "net_id": "000013",
                "ns_id": "EC656E0000000183",
                "tenant_id": "ttn",
                "cluster_id": "au1",
                "cluster_address": "au1.cloud.thethings.network"
            }
        }
    },
    {
        "end_device_ids": {
            "device_id": "em300-di",
            "application_ids": {
                "application_id": "daia-sensor-em300"
            },
            "dev_eui": "24E124136C482304",
            "join_eui": "24E124C0002A0001",
            "dev_addr": "260DA6E2"
        },
        "correlation_ids": [
            "gs:uplink:01JKPFVC93FRG0P6P9CJ84MJBX"
        ],
        "received_at": "2025-02-09T23:13:56.724776675Z",
        "uplink_message": {
            "session_key_id": "AZTN7na5Ikz11RtlE7G4bg==",
            "f_port": 85,
            "f_cnt": 1845,
            "frm_payload": "AXVjA2fuAARoSwXIBQsAAA==",
            "decoded_payload": {
                "battery": 99,
                "humidity": 37.5,
                "pulse": 2821,
                "temperature": 23.8
            },
            "rx_metadata": [
                {
                    "gateway_ids": {
                        "gateway_id": "daia-gateway",
                        "eui": "24E124FFFEFAF7FD"
                    },
                    "time": "2025-02-09T23:13:44.787Z",
                    "timestamp": 3843771125,
                    "rssi": -90,
                    "channel_rssi": -90,
                    "snr": 9.2,
                    "frequency_offset": "617",
                    "location": {
                        "latitude": -34.9861347413862,
                        "longitude": -71.238780895348,
                        "source": "SOURCE_REGISTRY"
                    },
                    "uplink_token": "ChoKGAoMZGFpYS1nYXRld2F5Eggk4ST//vr3/RD1le2oDhoMCLTtpL0GEProyvQBIIia85TvhHcqDAio7aS9BhDA1aL3Ag==",
                    "channel_index": 5,
                    "gps_time": "2025-02-09T23:13:44.787Z",
                    "received_at": "2025-02-09T23:13:56.352216450Z"
                }
            ],
            "settings": {
                "data_rate": {
                    "lora": {
                        "bandwidth": 125000,
                        "spreading_factor": 7,
                        "coding_rate": "4/5"
                    }
                },
                "frequency": "917800000",
                "timestamp": 3843771125,
                "time": "2025-02-09T23:13:44.787Z"
            },
            "received_at": "2025-02-09T23:13:56.516406334Z",
            "consumed_airtime": "0.066816s",
            "network_ids": {
                "net_id": "000013",
                "ns_id": "EC656E0000000183",
                "tenant_id": "ttn",
                "cluster_id": "au1",
                "cluster_address": "au1.cloud.thethings.network"
            }
        }
    },
    {
        "end_device_ids": {
            "device_id": "em300-di",
            "application_ids": {
                "application_id": "daia-sensor-em300"
            },
            "dev_eui": "24E124136C482304",
            "join_eui": "24E124C0002A0001",
            "dev_addr": "260DA6E2"
        },
        "correlation_ids": [
            "gs:uplink:01JKPG4H7VTJVM5FJB73NCYRZ3"
        ],
        "received_at": "2025-02-09T23:18:56.716324489Z",
        "uplink_message": {
            "session_key_id": "AZTN7na5Ikz11RtlE7G4bg==",
            "f_port": 85,
            "f_cnt": 1846,
            "frm_payload": "AXVjA2fuAARoTAXIBQsAAA==",
            "decoded_payload": {
                "battery": 99,
                "humidity": 38,
                "pulse": 2821,
                "temperature": 23.8
            },
            "rx_metadata": [
                {
                    "gateway_ids": {
                        "gateway_id": "daia-gateway",
                        "eui": "24E124FFFEFAF7FD"
                    },
                    "time": "2025-02-09T23:18:44.779Z",
                    "timestamp": 4143765422,
                    "rssi": -90,
                    "channel_rssi": -90,
                    "snr": 10.8,
                    "frequency_offset": "628",
                    "location": {
                        "latitude": -34.9861347413862,
                        "longitude": -71.238780895348,
                        "source": "SOURCE_REGISTRY"
                    },
                    "uplink_token": "ChoKGAoMZGFpYS1nYXRld2F5Eggk4ST//vr3/RCur/O3DxoMCODvpL0GEPSP6vABILD/qd3MjXcqDAjU76S9BhDAsbrzAg==",
                    "channel_index": 6,
                    "gps_time": "2025-02-09T23:18:44.779Z",
                    "received_at": "2025-02-09T23:18:56.344340732Z"
                }
            ],
            "settings": {
                "data_rate": {
                    "lora": {
                        "bandwidth": 125000,
                        "spreading_factor": 7,
                        "coding_rate": "4/5"
                    }
                },
                "frequency": "918000000",
                "timestamp": 4143765422,
                "time": "2025-02-09T23:18:44.779Z"
            },
            "received_at": "2025-02-09T23:18:56.508101975Z",
            "consumed_airtime": "0.066816s",
            "network_ids": {
                "net_id": "000013",
                "ns_id": "EC656E0000000183",
                "tenant_id": "ttn",
                "cluster_id": "au1",
                "cluster_address": "au1.cloud.thethings.network"
            }
        }
    },
    {
        "end_device_ids": {
            "device_id": "em300-di",
            "application_ids": {
                "application_id": "daia-sensor-em300"
            },
            "dev_eui": "24E124136C482304",
            "join_eui": "24E124C0002A0001",
            "dev_addr": "260DA6E2"
        },
        "correlation_ids": [
            "gs:uplink:01JKPGDP6MS5YEFZHQ5YCTXYV7"
        ],
        "received_at": "2025-02-09T23:23:56.707013582Z",
        "uplink_message": {
            "session_key_id": "AZTN7na5Ikz11RtlE7G4bg==",
            "f_port": 85,
            "f_cnt": 1847,
            "frm_payload": "AXVjA2fuAARoTQXIBQsAAA==",
            "decoded_payload": {
                "battery": 99,
                "humidity": 38.5,
                "pulse": 2821,
                "temperature": 23.8
            },
            "rx_metadata": [
                {
                    "gateway_ids": {
                        "gateway_id": "daia-gateway",
                        "eui": "24E124FFFEFAF7FD"
                    },
                    "time": "2025-02-09T23:23:44.771Z",
                    "timestamp": 148792352,
                    "rssi": -90,
                    "channel_rssi": -90,
                    "snr": 11,
                    "frequency_offset": "624",
                    "location": {
                        "latitude": -34.9861347413862,
                        "longitude": -71.238780895348,
                        "source": "SOURCE_REGISTRY"
                    },
                    "uplink_token": "ChoKGAoMZGFpYS1nYXRld2F5Eggk4ST//vr3/RCgyPlGGgwIjPKkvQYQrZzD7QEggLrcpaqWdyoMCIDypL0GEMCN0u8C",
                    "channel_index": 7,
                    "gps_time": "2025-02-09T23:23:44.771Z",
                    "received_at": "2025-02-09T23:23:56.337411893Z"
                }
            ],
            "settings": {
                "data_rate": {
                    "lora": {
                        "bandwidth": 125000,
                        "spreading_factor": 7,
                        "coding_rate": "4/5"
                    }
                },
                "frequency": "918200000",
                "timestamp": 148792352,
                "time": "2025-02-09T23:23:44.771Z"
            },
            "received_at": "2025-02-09T23:23:56.501241476Z",
            "consumed_airtime": "0.066816s",
            "network_ids": {
                "net_id": "000013",
                "ns_id": "EC656E0000000183",
                "tenant_id": "ttn",
                "cluster_id": "au1",
                "cluster_address": "au1.cloud.thethings.network"
            }
        }
    },
    {
        "end_device_ids": {
            "device_id": "em300-di",
            "application_ids": {
                "application_id": "daia-sensor-em300"
            },
            "dev_eui": "24E124136C482304",
            "join_eui": "24E124C0002A0001",
            "dev_addr": "260DA6E2"
        },
        "correlation_ids": [
            "gs:uplink:01JKPGPV5B67E4H92XX5AGE69K"
        ],
        "received_at": "2025-02-09T23:28:56.699045593Z",
        "uplink_message": {
            "session_key_id": "AZTN7na5Ikz11RtlE7G4bg==",
            "f_port": 85,
            "f_cnt": 1848,
            "frm_payload": "AXVjA2ftAARoTAXIBQsAAA==",
            "decoded_payload": {
                "battery": 99,
                "humidity": 38,
                "pulse": 2821,
                "temperature": 23.7
            },
            "rx_metadata": [
                {
                    "gateway_ids": {
                        "gateway_id": "daia-gateway",
                        "eui": "24E124FFFEFAF7FD"
                    },
                    "time": "2025-02-09T23:28:44.755Z",
                    "timestamp": 448778517,
                    "rssi": -89,
                    "channel_rssi": -89,
                    "snr": 9.8,
                    "frequency_offset": "689",
                    "location": {
                        "latitude": -34.9861347413862,
                        "longitude": -71.238780895348,
                        "source": "SOURCE_REGISTRY"
                    },
                    "uplink_token": "ChoKGAoMZGFpYS1nYXRld2F5Eggk4ST//vr3/RCVov/VARoMCLj0pL0GEOrWrekBIIj0ouqHn3cqDAis9KS9BhDAxYHoAg==",
                    "channel_index": 2,
                    "gps_time": "2025-02-09T23:28:44.755Z",
                    "received_at": "2025-02-09T23:28:56.328670322Z"
                }
            ],
            "settings": {
                "data_rate": {
                    "lora": {
                        "bandwidth": 125000,
                        "spreading_factor": 7,
                        "coding_rate": "4/5"
                    }
                },
                "frequency": "917200000",
                "timestamp": 448778517,
                "time": "2025-02-09T23:28:44.755Z"
            },
            "received_at": "2025-02-09T23:28:56.492452921Z",
            "consumed_airtime": "0.071936s",
            "network_ids": {
                "net_id": "000013",
                "ns_id": "EC656E0000000183",
                "tenant_id": "ttn",
                "cluster_id": "au1",
                "cluster_address": "au1.cloud.thethings.network"
            }
        }
    },
    {
        "end_device_ids": {
            "device_id": "em300-di",
            "application_ids": {
                "application_id": "daia-sensor-em300"
            },
            "dev_eui": "24E124136C482304",
            "join_eui": "24E124C0002A0001",
            "dev_addr": "260DA6E2"
        },
        "correlation_ids": [
            "gs:uplink:01JKPH003SKHNYFHZEZVGD23F8"
        ],
        "received_at": "2025-02-09T23:33:56.681229517Z",
        "uplink_message": {
            "session_key_id": "AZTN7na5Ikz11RtlE7G4bg==",
            "f_port": 85,
            "f_cnt": 1849,
            "frm_payload": "AXVjA2ftAARoTAXIBQsAAA==",
            "decoded_payload": {
                "battery": 99,
                "humidity": 38,
                "pulse": 2821,
                "temperature": 23.7
            },
            "rx_metadata": [
                {
                    "gateway_ids": {
                        "gateway_id": "daia-gateway",
                        "eui": "24E124FFFEFAF7FD"
                    },
                    "time": "2025-02-09T23:33:44.741Z",
                    "timestamp": 748766561,
                    "rssi": -91,
                    "channel_rssi": -91,
                    "snr": 10.2,
                    "frequency_offset": "677",
                    "location": {
                        "latitude": -34.9861347413862,
                        "longitude": -71.238780895348,
                        "source": "SOURCE_REGISTRY"
                    },
                    "uplink_token": "ChoKGAoMZGFpYS1nYXRld2F5Eggk4ST//vr3/RDhioXlAhoMCOT2pL0GEPmb7+ABIOiF3K/lp3cqDAjY9qS9BhDAhqvhAg==",
                    "channel_index": 3,
                    "gps_time": "2025-02-09T23:33:44.741Z",
                    "received_at": "2025-02-09T23:33:56.310354507Z"
                }
            ],
            "settings": {
                "data_rate": {
                    "lora": {
                        "bandwidth": 125000,
                        "spreading_factor": 7,
                        "coding_rate": "4/5"
                    }
                },
                "frequency": "917400000",
                "timestamp": 748766561,
                "time": "2025-02-09T23:33:44.741Z"
            },
            "received_at": "2025-02-09T23:33:56.474831406Z",
            "consumed_airtime": "0.066816s",
            "network_ids": {
                "net_id": "000013",
                "ns_id": "EC656E0000000183",
                "tenant_id": "ttn",
                "cluster_id": "au1",
                "cluster_address": "au1.cloud.thethings.network"
            }
        }
    },
    {
        "end_device_ids": {
            "device_id": "em300-di",
            "application_ids": {
                "application_id": "daia-sensor-em300"
            },
            "dev_eui": "24E124136C482304",
            "join_eui": "24E124C0002A0001",
            "dev_addr": "260DA6E2"
        },
        "correlation_ids": [
            "gs:uplink:01JKPH952KPZA5XGD9BT5YV5XP"
        ],
        "received_at": "2025-02-09T23:38:56.677305848Z",
        "uplink_message": {
            "session_key_id": "AZTN7na5Ikz11RtlE7G4bg==",
            "f_port": 85,
            "f_cnt": 1850,
            "frm_payload": "AXVjA2fsAARoTgXIBQsAAA==",
            "decoded_payload": {
                "battery": 99,
                "humidity": 39,
                "pulse": 2821,
                "temperature": 23.6
            },
            "rx_metadata": [
                {
                    "gateway_ids": {
                        "gateway_id": "daia-gateway",
                        "eui": "24E124FFFEFAF7FD"
                    },
                    "time": "2025-02-09T23:38:44.733Z",
                    "timestamp": 1048760763,
                    "rssi": -87,
                    "channel_rssi": -87,
                    "snr": 12.2,
                    "frequency_offset": "683",
                    "location": {
                        "latitude": -34.9861347413862,
                        "longitude": -71.238780895348,
                        "source": "SOURCE_REGISTRY"
                    },
                    "uplink_token": "ChoKGAoMZGFpYS1nYXRld2F5Eggk4ST//vr3/RC7o4v0AxoMCJD5pL0GELmS390BIPiEjfjCsHcqDAiE+aS9BhDA4sLdAg==",
                    "gps_time": "2025-02-09T23:38:44.733Z",
                    "received_at": "2025-02-09T23:38:56.303799691Z"
                }
            ],
            "settings": {
                "data_rate": {
                    "lora": {
                        "bandwidth": 125000,
                        "spreading_factor": 7,
                        "coding_rate": "4/5"
                    }
                },
                "frequency": "916800000",
                "timestamp": 1048760763,
                "time": "2025-02-09T23:38:44.733Z"
            },
            "received_at": "2025-02-09T23:38:56.467974104Z",
            "consumed_airtime": "0.066816s",
            "network_ids": {
                "net_id": "000013",
                "ns_id": "EC656E0000000183",
                "tenant_id": "ttn",
                "cluster_id": "au1",
                "cluster_address": "au1.cloud.thethings.network"
            }
        }
    },
    {
        "end_device_ids": {
            "device_id": "em300-di",
            "application_ids": {
                "application_id": "daia-sensor-em300"
            },
            "dev_eui": "24E124136C482304",
            "join_eui": "24E124C0002A0001",
            "dev_addr": "260DA6E2"
        },
        "correlation_ids": [
            "gs:uplink:01JKPHJA1MNSC4S518BZGTCEJF"
        ],
        "received_at": "2025-02-09T23:43:56.675700419Z",
        "uplink_message": {
            "session_key_id": "AZTN7na5Ikz11RtlE7G4bg==",
            "f_port": 85,
            "f_cnt": 1851,
            "frm_payload": "AXVjA2frAARoUAXIBQsAAA==",
            "decoded_payload": {
                "battery": 99,
                "humidity": 40,
                "pulse": 2821,
                "temperature": 23.5
            },
            "rx_metadata": [
                {
                    "gateway_ids": {
                        "gateway_id": "daia-gateway",
                        "eui": "24E124FFFEFAF7FD"
                    },
                    "time": "2025-02-09T23:43:44.725Z",
                    "timestamp": 1348755260,
                    "rssi": -92,
                    "channel_rssi": -92,
                    "snr": 9.8,
                    "frequency_offset": "599",
                    "location": {
                        "latitude": -34.9861347413862,
                        "longitude": -71.238780895348,
                        "source": "SOURCE_REGISTRY"
                    },
                    "uplink_token": "ChoKGAoMZGFpYS1nYXRld2F5Eggk4ST//vr3/RC8vpGDBRoMCLz7pL0GEJq6q94BIOCE0MCguXcqDAiw+6S9BhDAvtrZAg==",
                    "channel_index": 4,
                    "gps_time": "2025-02-09T23:43:44.725Z",
                    "received_at": "2025-02-09T23:43:56.305172322Z"
                }
            ],
            "settings": {
                "data_rate": {
                    "lora": {
                        "bandwidth": 125000,
                        "spreading_factor": 7,
                        "coding_rate": "4/5"
                    }
                },
                "frequency": "917600000",
                "timestamp": 1348755260,
                "time": "2025-02-09T23:43:44.725Z"
            },
            "received_at": "2025-02-09T23:43:56.469330206Z",
            "consumed_airtime": "0.071936s",
            "network_ids": {
                "net_id": "000013",
                "ns_id": "EC656E0000000183",
                "tenant_id": "ttn",
                "cluster_id": "au1",
                "cluster_address": "au1.cloud.thethings.network"
            }
        }
    },
    {
        "end_device_ids": {
            "device_id": "em300-di",
            "application_ids": {
                "application_id": "daia-sensor-em300"
            },
            "dev_eui": "24E124136C482304",
            "join_eui": "24E124C0002A0001",
            "dev_addr": "260DA6E2"
        },
        "correlation_ids": [
            "gs:uplink:01JKPHVF0C3W0A1VRP87167089"
        ],
        "received_at": "2025-02-09T23:48:56.666438765Z",
        "uplink_message": {
            "session_key_id": "AZTN7na5Ikz11RtlE7G4bg==",
            "f_port": 85,
            "f_cnt": 1852,
            "frm_payload": "AXVjA2frAARoUQXIBQsAAA==",
            "decoded_payload": {
                "battery": 99,
                "humidity": 40.5,
                "pulse": 2821,
                "temperature": 23.5
            },
            "rx_metadata": [
                {
                    "gateway_ids": {
                        "gateway_id": "daia-gateway",
                        "eui": "24E124FFFEFAF7FD"
                    },
                    "time": "2025-02-09T23:48:44.717Z",
                    "timestamp": 1648749275,
                    "rssi": -90,
                    "channel_rssi": -90,
                    "snr": 9.5,
                    "frequency_offset": "671",
                    "location": {
                        "latitude": -34.9861347413862,
                        "longitude": -71.238780895348,
                        "source": "SOURCE_REGISTRY"
                    },
                    "uplink_token": "ChoKGAoMZGFpYS1nYXRld2F5Eggk4ST//vr3/RDb1ZeSBhoMCOj9pL0GEK2009oBIPjO9Yj+wXcqDAjc/aS9BhDAmvLVAg==",
                    "channel_index": 1,
                    "gps_time": "2025-02-09T23:48:44.717Z",
                    "received_at": "2025-02-09T23:48:56.297438325Z"
                }
            ],
            "settings": {
                "data_rate": {
                    "lora": {
                        "bandwidth": 125000,
                        "spreading_factor": 7,
                        "coding_rate": "4/5"
                    }
                },
                "frequency": "917000000",
                "timestamp": 1648749275,
                "time": "2025-02-09T23:48:44.717Z"
            },
            "received_at": "2025-02-09T23:48:56.461567801Z",
            "consumed_airtime": "0.066816s",
            "network_ids": {
                "net_id": "000013",
                "ns_id": "EC656E0000000183",
                "tenant_id": "ttn",
                "cluster_id": "au1",
                "cluster_address": "au1.cloud.thethings.network"
            }
        }
    },
    {
        "end_device_ids": {
            "device_id": "em300-di",
            "application_ids": {
                "application_id": "daia-sensor-em300"
            },
            "dev_eui": "24E124136C482304",
            "join_eui": "24E124C0002A0001",
            "dev_addr": "260DA6E2"
        },
        "correlation_ids": [
            "gs:uplink:01JKPJ4KZ4JK2H6X3CEHTA1KD3"
        ],
        "received_at": "2025-02-09T23:53:56.659633126Z",
        "uplink_message": {
            "session_key_id": "AZTN7na5Ikz11RtlE7G4bg==",
            "f_port": 85,
            "f_cnt": 1853,
            "frm_payload": "AXVjA2frAARoUQXIBQsAAA==",
            "decoded_payload": {
                "battery": 99,
                "humidity": 40.5,
                "pulse": 2821,
                "temperature": 23.5
            },
            "rx_metadata": [
                {
                    "gateway_ids": {
                        "gateway_id": "daia-gateway",
                        "eui": "24E124FFFEFAF7FD"
                    },
                    "time": "2025-02-09T23:53:44.708Z",
                    "timestamp": 1948743515,
                    "rssi": -92,
                    "channel_rssi": -92,
                    "snr": 9.5,
                    "frequency_offset": "670",
                    "location": {
                        "latitude": -34.9861347413862,
                        "longitude": -71.238780895348,
                        "source": "SOURCE_REGISTRY"
                    },
                    "uplink_token": "ChoKGAoMZGFpYS1nYXRld2F5Eggk4ST//vr3/RDb7p2hBxoMCJSApb0GEL6N2tYBIPj2qNHbyncqDAiIgKW9BhCA8szRAg==",
                    "channel_index": 3,
                    "gps_time": "2025-02-09T23:53:44.708Z",
                    "received_at": "2025-02-09T23:53:56.289159430Z"
                }
            ],
            "settings": {
                "data_rate": {
                    "lora": {
                        "bandwidth": 125000,
                        "spreading_factor": 7,
                        "coding_rate": "4/5"
                    }
                },
                "frequency": "917400000",
                "timestamp": 1948743515,
                "time": "2025-02-09T23:53:44.708Z"
            },
            "received_at": "2025-02-09T23:53:56.453750572Z",
            "consumed_airtime": "0.066816s",
            "network_ids": {
                "net_id": "000013",
                "ns_id": "EC656E0000000183",
                "tenant_id": "ttn",
                "cluster_id": "au1",
                "cluster_address": "au1.cloud.thethings.network"
            }
        }
    },
    {
        "end_device_ids": {
            "device_id": "em300-di",
            "application_ids": {
                "application_id": "daia-sensor-em300"
            },
            "dev_eui": "24E124136C482304",
            "join_eui": "24E124C0002A0001",
            "dev_addr": "260DA6E2"
        },
        "correlation_ids": [
            "gs:uplink:01JKPJDRXX8W8WGKBTCKNAY782"
        ],
        "received_at": "2025-02-09T23:58:56.652807859Z",
        "uplink_message": {
            "session_key_id": "AZTN7na5Ikz11RtlE7G4bg==",
            "f_port": 85,
            "f_cnt": 1854,
            "frm_payload": "AXVjA2frAARoUgXIBQsAAA==",
            "decoded_payload": {
                "battery": 99,
                "humidity": 41,
                "pulse": 2821,
                "temperature": 23.5
            },
            "rx_metadata": [
                {
                    "gateway_ids": {
                        "gateway_id": "daia-gateway",
                        "eui": "24E124FFFEFAF7FD"
                    },
                    "time": "2025-02-09T23:58:44.700Z",
                    "timestamp": 2248737739,
                    "rssi": -92,
                    "channel_rssi": -92,
                    "snr": 8.8,
                    "frequency_offset": "610",
                    "location": {
                        "latitude": -34.9861347413862,
                        "longitude": -71.238780895348,
                        "source": "SOURCE_REGISTRY"
                    },
                    "uplink_token": "ChoKGAoMZGFpYS1nYXRld2F5Eggk4ST//vr3/RDLh6SwCBoMCMCCpb0GEPXNxtMBIPih25m503cqDAi0gqW9BhCAzuTNAg==",
                    "channel_index": 5,
                    "gps_time": "2025-02-09T23:58:44.700Z",
                    "received_at": "2025-02-09T23:58:56.282548541Z"
                }
            ],
            "settings": {
                "data_rate": {
                    "lora": {
                        "bandwidth": 125000,
                        "spreading_factor": 7,
                        "coding_rate": "4/5"
                    }
                },
                "frequency": "917800000",
                "timestamp": 2248737739,
                "time": "2025-02-09T23:58:44.700Z"
            },
            "received_at": "2025-02-09T23:58:56.446888213Z",
            "consumed_airtime": "0.066816s",
            "network_ids": {
                "net_id": "000013",
                "ns_id": "EC656E0000000183",
                "tenant_id": "ttn",
                "cluster_id": "au1",
                "cluster_address": "au1.cloud.thethings.network"
            }
        }
    }
]